[
    {
        "id": "115",
        "eventId": 1,
        "ageDivision": "1-5",
        "title": "Dummy Roping",
        "titleShort": "DR",
        "order": 1,
        "entryFee": 10,
        "type": "Ground",
        "isLeadLineClass": false
    },
    {
        "id": "168",
        "eventId": 1,
        "ageDivision": "6-8",
        "title": "Dummy Roping",
        "titleShort": "DR",
        "order": 1,
        "entryFee": 10,
        "type": "Ground",
        "isLeadLineClass": false
    },
    {
        "id": "1912",
        "eventId": 1,
        "ageDivision": "9-12",
        "title": "Dummy Roping",
        "titleShort": "DR",
        "order": 1,
        "entryFee": 10,
        "type": "Ground",
        "isLeadLineClass": false
    },
    {
        "id": "215",
        "eventId": 2,
        "ageDivision": "1-5",
        "title": "Stick Horse Race",
        "titleShort": "STR",
        "order": 2,
        "entryFee": 10,
        "type": "Ground",
        "isLeadLineClass": false
    },
    {
        "id": "315",
        "eventId": 3,
        "ageDivision": "1-5",
        "title": "Ribbon Pull",
        "titleShort": "RP",
        "order": 3,
        "entryFee": 10,
        "type": "Ground",
        "isLeadLineClass": false
    },
    {
        "id": "468",
        "eventId": 4,
        "ageDivision": "6-8",
        "title": "Unmounted Goat Tying",
        "titleShort": "UGT",
        "order": 4,
        "entryFee": 15,
        "type": "Ground",
        "isLeadLineClass": false
    },
    {
        "id": "4912",
        "eventId": 4,
        "ageDivision": "9-12",
        "title": "Unmounted Goat Tying",
        "titleShort": "UGT",
        "order": 4,
        "entryFee": 15,
        "type": "Ground",
        "isLeadLineClass": false
    },
    {
        "id": "568",
        "eventId": 5,
        "ageDivision": "6-8",
        "title": "Mounted Goat Tying",
        "titleShort": "GT",
        "order": 3,
        "entryFee": 20,
        "type": "Mounted",
        "isLeadLineClass": false
    },
    {
        "id": "5912",
        "eventId": 5,
        "ageDivision": "9-12",
        "title": "Mounted Goat Tying",
        "titleShort": "GT",
        "order": 3,
        "entryFee": 20,
        "type": "Mounted",
        "isLeadLineClass": false
    },
    {
        "id": "51315",
        "eventId": 5,
        "ageDivision": "13-15",
        "title": "Mounted Goat Tying",
        "titleShort": "GT",
        "order": 3,
        "entryFee": 20,
        "type": "Mounted",
        "isLeadLineClass": false
    },
    {
        "id": "51619",
        "eventId": 5,
        "ageDivision": "16-19",
        "title": "Mounted Goat Tying",
        "titleShort": "GT",
        "order": 3,
        "entryFee": 20,
        "type": "Mounted",
        "isLeadLineClass": false
    },
    {
        "id": "6912",
        "eventId": 6,
        "ageDivision": "9-12",
        "title": "Chute Dogging",
        "titleShort": "CD",
        "order": 5,
        "entryFee": 25,
        "type": "Ground",
        "isLeadLineClass": false
    },
    {
        "id": "61315",
        "eventId": 6,
        "ageDivision": "13-15",
        "title": "Chute Dogging",
        "titleShort": "CD",
        "order": 5,
        "entryFee": 25,
        "type": "Ground",
        "isLeadLineClass": false
    },
    {
        "id": "61619",
        "eventId": 6,
        "ageDivision": "16-19",
        "title": "Chute Dogging",
        "titleShort": "CD",
        "order": 5,
        "entryFee": 25,
        "type": "Ground",
        "isLeadLineClass": false
    },
    {
        "id": "768",
        "eventId": 7,
        "ageDivision": "6-8",
        "title": "Flank and Tie",
        "titleShort": "FT",
        "order": 6,
        "entryFee": 25,
        "type": "Ground",
        "isLeadLineClass": false
    },
    {
        "id": "7912",
        "eventId": 7,
        "ageDivision": "9-12",
        "title": "Flank and Tie",
        "titleShort": "FT",
        "order": 6,
        "entryFee": 25,
        "type": "Ground",
        "isLeadLineClass": false
    },
    {
        "id": "71315",
        "eventId": 7,
        "ageDivision": "13-15",
        "title": "Flank and Tie",
        "titleShort": "FT",
        "order": 6,
        "entryFee": 25,
        "type": "Ground",
        "isLeadLineClass": false
    },
    {
        "id": "868",
        "eventId": 8,
        "ageDivision": "6-8",
        "title": "Breakaway",
        "titleShort": "BK",
        "order": 4,
        "entryFee": 25,
        "type": "Mounted",
        "isLeadLineClass": false
    },
    {
        "id": "8912",
        "eventId": 8,
        "ageDivision": "9-12",
        "title": "Breakaway",
        "titleShort": "BK",
        "order": 4,
        "entryFee": 25,
        "type": "Mounted",
        "isLeadLineClass": false
    },
    {
        "id": "81315",
        "eventId": 8,
        "ageDivision": "13-15",
        "title": "Breakaway",
        "titleShort": "BK",
        "order": 4,
        "entryFee": 25,
        "type": "Mounted",
        "isLeadLineClass": false
    },
    {
        "id": "81619",
        "eventId": 8,
        "ageDivision": "16-19",
        "title": "Breakaway",
        "titleShort": "BK",
        "order": 4,
        "entryFee": 25,
        "type": "Mounted",
        "isLeadLineClass": false
    },
    {
        "id": "9912",
        "eventId": 9,
        "ageDivision": "9-12",
        "title": "Calf Roping",
        "titleShort": "CR",
        "order": 5,
        "entryFee": 25,
        "type": "Mounted",
        "isLeadLineClass": false
    },
    {
        "id": "91315",
        "eventId": 9,
        "ageDivision": "13-15",
        "title": "Calf Roping",
        "titleShort": "CR",
        "order": 5,
        "entryFee": 25,
        "type": "Mounted",
        "isLeadLineClass": false
    },
    {
        "id": "91619",
        "eventId": 9,
        "ageDivision": "16-19",
        "title": "Calf Roping",
        "titleShort": "CR",
        "order": 5,
        "entryFee": 25,
        "type": "Mounted",
        "isLeadLineClass": false
    },
    {
        "id": "1068",
        "eventId": 10,
        "ageDivision": "6-8",
        "title": "Steer Stopping",
        "titleShort": "SS",
        "order": 6,
        "entryFee": 25,
        "type": "Mounted",
        "isLeadLineClass": false
    },
    {
        "id": "10912",
        "eventId": 10,
        "ageDivision": "9-12",
        "title": "Steer Stopping",
        "titleShort": "SS",
        "order": 6,
        "entryFee": 25,
        "type": "Mounted",
        "isLeadLineClass": false
    },
    {
        "id": "101315",
        "eventId": 10,
        "ageDivision": "13-15",
        "title": "Steer Stopping",
        "titleShort": "SS",
        "order": 6,
        "entryFee": 25,
        "type": "Mounted",
        "isLeadLineClass": false
    },
    {
        "id": "101619",
        "eventId": 10,
        "ageDivision": "16-19",
        "title": "Steer Stopping",
        "titleShort": "SS",
        "order": 6,
        "entryFee": 25,
        "type": "Mounted",
        "isLeadLineClass": false
    },
    {
        "id": "1315",
        "eventId": 13,
        "ageDivision": "1-5",
        "title": "Pole Bending",
        "titleShort": "PB",
        "order": 1,
        "entryFee": 20,
        "type": "Mounted",
        "isLeadLineClass": false
    },
    {
        "id": "1315LL",
        "eventId": 13,
        "ageDivision": "1-5",
        "title": "Pole Bending",
        "titleShort": "PB",
        "order": 1,
        "entryFee": 7,
        "type": "Mounted",
        "isLeadLineClass": true
    },
    {
        "id": "1368",
        "eventId": 13,
        "ageDivision": "6-8",
        "title": "Pole Bending",
        "titleShort": "PB",
        "order": 1,
        "entryFee": 20,
        "type": "Mounted",
        "isLeadLineClass": false
    },
    {
        "id": "13912",
        "eventId": 13,
        "ageDivision": "9-12",
        "title": "Pole Bending",
        "titleShort": "PB",
        "order": 1,
        "entryFee": 20,
        "type": "Mounted",
        "isLeadLineClass": false
    },
    {
        "id": "131315",
        "eventId": 13,
        "ageDivision": "13-15",
        "title": "Pole Bending",
        "titleShort": "PB",
        "order": 1,
        "entryFee": 20,
        "type": "Mounted",
        "isLeadLineClass": false
    },
    {
        "id": "131619",
        "eventId": 13,
        "ageDivision": "16-19",
        "title": "Pole Bending",
        "titleShort": "PB",
        "order": 1,
        "entryFee": 20,
        "type": "Mounted",
        "isLeadLineClass": false
    },
    {
        "id": "11919",
        "eventId": 11,
        "ageDivision": "9-19",
        "title": "Heading",
        "titleShort": "HD",
        "order": 7,
        "entryFee": 20,
        "type": "Mounted",
        "isLeadLineClass": false
    },
    {
        "id": "11919",
        "eventId": 11,
        "ageDivision": "9-19",
        "title": "Heading",
        "titleShort": "HD",
        "order": 7,
        "entryFee": 20,
        "type": "Mounted",
        "isLeadLineClass": false
    },
    {
        "id": "11919",
        "eventId": 11,
        "ageDivision": "9-19",
        "title": "Heading",
        "titleShort": "HD",
        "order": 7,
        "entryFee": 20,
        "type": "Mounted",
        "isLeadLineClass": false
    },
    {
        "id": "12919",
        "eventId": 12,
        "ageDivision": "9-19",
        "title": "Heeling",
        "titleShort": "HL",
        "order": 7,
        "entryFee": 20,
        "type": "Mounted",
        "isLeadLineClass": false
    },
    {
        "id": "12919",
        "eventId": 12,
        "ageDivision": "9-19",
        "title": "Heeling",
        "titleShort": "HL",
        "order": 7,
        "entryFee": 20,
        "type": "Mounted",
        "isLeadLineClass": false
    },
    {
        "id": "12919",
        "eventId": 12,
        "ageDivision": "9-19",
        "title": "Heeling",
        "titleShort": "HL",
        "order": 7,
        "entryFee": 20,
        "type": "Mounted",
        "isLeadLineClass": false
    },
    {
        "id": "1415",
        "eventId": 14,
        "ageDivision": "1-5",
        "title": "Barrel Racing",
        "titleShort": "BR",
        "order": 2,
        "entryFee": 20,
        "type": "Mounted",
        "isLeadLineClass": false
    },
    {
        "id": "1415LL",
        "eventId": 14,
        "ageDivision": "1-5",
        "title": "Barrel Racing",
        "titleShort": "BR",
        "order": 2,
        "entryFee": 7,
        "type": "Mounted",
        "isLeadLineClass": true
    },
    {
        "id": "1468",
        "eventId": 14,
        "ageDivision": "6-8",
        "title": "Barrel Racing",
        "titleShort": "BR",
        "order": 2,
        "entryFee": 20,
        "type": "Mounted",
        "isLeadLineClass": false
    },
    {
        "id": "14912",
        "eventId": 14,
        "ageDivision": "9-12",
        "title": "Barrel Racing",
        "titleShort": "BR",
        "order": 2,
        "entryFee": 20,
        "type": "Mounted",
        "isLeadLineClass": false
    },
    {
        "id": "141315",
        "eventId": 14,
        "ageDivision": "13-15",
        "title": "Barrel Racing",
        "titleShort": "BR",
        "order": 2,
        "entryFee": 20,
        "type": "Mounted",
        "isLeadLineClass": false
    },
    {
        "id": "141619",
        "eventId": 14,
        "ageDivision": "16-19",
        "title": "Barrel Racing",
        "titleShort": "BR",
        "order": 2,
        "entryFee": 20,
        "type": "Mounted",
        "isLeadLineClass": false
    }
]
